{
  "1787629": {
    "title": "\"Split out yaru-theme-gtk2\"",
    "link": "https://bugs.launchpad.net/ubuntu/+source/yaru-theme/+bug/1787629"
  },
  "1896334": {
    "title": "\"SRU 3.36.6\"",
    "link": "https://bugs.launchpad.net/ubuntu/+source/yaru-theme/+bug/1896334"
  },
  "1899283": {
    "title": "\"[UIFe] New Yaru theme with upstream fixes\"",
    "link": "https://bugs.launchpad.net/ubuntu/+source/yaru-theme/+bug/1899283"
  },
  "1795745": {
    "title": "\"Combobox opens at wrong vertical position\"",
    "link": "https://bugs.launchpad.net/ubuntu/+source/yaru-theme/+bug/1795745"
  },
  "1852091": {
    "title": "\"No icon for VirtualboxVM\"",
    "link": "https://bugs.launchpad.net/ubuntu/+source/yaru-theme/+bug/1852091"
  },
  "1873365": {
    "title": "\"gedit icon is too pale\"",
    "link": "https://bugs.launchpad.net/ubuntu/+source/yaru-theme/+bug/1873365"
  },
  "1878998": {
    "title": "\"Value in Yaru-dark/gnome-shell/gnome-shell.css not used\"",
    "link": "https://bugs.launchpad.net/ubuntu/+source/yaru-theme/+bug/1878998"
  },
  "1889991": {
    "title": "\"Highlight for the task switcher is too subtle\"",
    "link": "https://bugs.launchpad.net/ubuntu/+source/yaru-theme/+bug/1889991"
  },
  "1707831": {
    "title": "\"[enhancement] Replace/extend the \"Activities\" label with the Ubuntu icon/logo/glyph\"",
    "link": "https://bugs.launchpad.net/ubuntu/+source/yaru-theme/+bug/1707831"
  },
  "1787969": {
    "title": "\"Upload yaru-theme to Debian and maintain it there\"",
    "link": "https://bugs.launchpad.net/ubuntu/+source/yaru-theme/+bug/1787969"
  },
  "1873346": {
    "title": "\"Remove the grey border/background from the Files (nautilus) icon\"",
    "link": "https://bugs.launchpad.net/ubuntu/+source/yaru-theme/+bug/1873346"
  },
  "1875993": {
    "title": "\"yaru-theme-icon missing category icons\"",
    "link": "https://bugs.launchpad.net/ubuntu/+source/yaru-theme/+bug/1875993"
  },
  "1792604": {
    "title": "\"Installing yaru should try to remove the communitheme snap\"",
    "link": "https://bugs.launchpad.net/ubuntu/+source/yaru-theme/+bug/1792604"
  },
  "1842886": {
    "title": "\"Yaru-dark shell menus and dialogs are not dark\"",
    "link": "https://bugs.launchpad.net/ubuntu/+source/yaru-theme/+bug/1842886"
  },
  "1857191": {
    "title": "\"Dark themes don't work well with highlighted current line in gedit\"",
    "link": "https://bugs.launchpad.net/ubuntu/+source/yaru-theme/+bug/1857191"
  },
  "1871386": {
    "title": "\"Duplicate CSS Yaru-dark gnome-shell theme\"",
    "link": "https://bugs.launchpad.net/ubuntu/+source/yaru-theme/+bug/1871386"
  },
  "1899261": {
    "title": "\"gnome 3.38 app's CSD header bar buttons are cropped\"",
    "link": "https://bugs.launchpad.net/ubuntu/+source/yaru-theme/+bug/1899261"
  }
}